Metadata-Version: 1.1
Name: sitesearcher
Version: 0.1a2
Summary: A command line tool that creates fulltext search indexes of your favourite websites on your machine, and allows you to search them locally
Home-page: UNKNOWN
Author: Sebastian Brass (sbabrass)
Author-email: UNKNOWN
License: BSD-derived (http://www.repoze.org/LICENSE.txt)
Keywords: scrapy whoosh searching indexing websearch
Platform: UNKNOWN
Classifier: Programming Language :: Python
Classifier: Programming Language :: Python :: 2.7
Classifier: Programming Language :: Python :: 3
Classifier: Topic :: Internet :: WWW/HTTP :: Indexing/Search
Classifier: License :: Repoze Public License
